dotstrings/__init__.py
dotstrings/dot_strings_entry.py
dotstrings/dot_stringsdict_entry.py
dotstrings/exceptions.py
dotstrings/genstrings.py
dotstrings/localized_bundle.py
dotstrings/localized_string.py
dotstrings/parser.py
dotstrings-3.1.4.dist-info/LICENSE
dotstrings-3.1.4.dist-info/METADATA
dotstrings-3.1.4.dist-info/WHEEL
dotstrings-3.1.4.dist-info/RECORD
