Metadata-Version: 2.1
Name: dotstrings
Version: 3.1.4
Summary: Tools for dealing with the .strings files for iOS and macOS
Home-page: https://github.com/Microsoft/dotstrings
License: MIT
Keywords: localization,iOS,macOS,strings
Author: Dale Myers
Author-email: dalemyers@microsoft.com
Requires-Python: >=3.10,<4.0
Classifier: Development Status :: 5 - Production/Stable
Classifier: Environment :: Console
Classifier: Environment :: MacOS X
Classifier: Intended Audience :: Developers
Classifier: License :: OSI Approved :: MIT License
Classifier: Programming Language :: Python :: 3
Classifier: Programming Language :: Python :: 3.10
Classifier: Programming Language :: Python :: 3.11
Classifier: Programming Language :: Python :: 3.12
Classifier: Programming Language :: Python :: 3.13
Classifier: Programming Language :: Python :: 3.8
Classifier: Programming Language :: Python :: 3.9
Classifier: Topic :: Software Development
Classifier: Topic :: Utilities
Project-URL: Repository, https://github.com/Microsoft/dotstrings
